MANIFEST.in
requirements.txt
setup.py
test_requirements.txt
version.txt
cloudshell/__init__.py
cloudshell/firewall/__init__.py
cloudshell/firewall/cisco/__init__.py
cloudshell/firewall/cisco/asa/__init__.py
cloudshell/firewall/cisco/asa/autoload/__init__.py
cloudshell/firewall/cisco/asa/autoload/cisco_asa_snmp_autoload.py
cloudshell/firewall/cisco/asa/cli/__init__.py
cloudshell/firewall/cisco/asa/cli/cisco_asa_cli_handler.py
cloudshell/firewall/cisco/asa/cli/cisco_asa_command_modes.py
cloudshell/firewall/cisco/asa/command_actions/__init__.py
cloudshell/firewall/cisco/asa/command_actions/enable_disable_snmp_actions.py
cloudshell/firewall/cisco/asa/command_actions/iface_actions.py
cloudshell/firewall/cisco/asa/command_actions/system_actions.py
cloudshell/firewall/cisco/asa/command_templates/__init__.py
cloudshell/firewall/cisco/asa/command_templates/configuration.py
cloudshell/firewall/cisco/asa/command_templates/enable_disable_snmp.py
cloudshell/firewall/cisco/asa/command_templates/firmware.py
cloudshell/firewall/cisco/asa/command_templates/iface.py
cloudshell/firewall/cisco/asa/flows/__init__.py
cloudshell/firewall/cisco/asa/flows/cisco_asa_autoload_flow.py
cloudshell/firewall/cisco/asa/flows/cisco_asa_disable_snmp_flow.py
cloudshell/firewall/cisco/asa/flows/cisco_asa_enable_snmp_flow.py
cloudshell/firewall/cisco/asa/flows/cisco_asa_load_firmware_flow.py
cloudshell/firewall/cisco/asa/flows/cisco_asa_restore_flow.py
cloudshell/firewall/cisco/asa/flows/cisco_asa_save_flow.py
cloudshell/firewall/cisco/asa/mibs/CISCO-CDP-MIB.py
cloudshell/firewall/cisco/asa/mibs/CISCO-ENTITY-VENDORTYPE-OID-MIB.py
cloudshell/firewall/cisco/asa/mibs/CISCO-PRODUCTS-MIB.py
cloudshell/firewall/cisco/asa/mibs/CISCO-SMI.py
cloudshell/firewall/cisco/asa/mibs/CISCO-STACK-MIB.py
cloudshell/firewall/cisco/asa/mibs/CISCO-TC.py
cloudshell/firewall/cisco/asa/mibs/CISCO-VTP-MIB.py
cloudshell/firewall/cisco/asa/mibs/__init__.py
cloudshell/firewall/cisco/asa/runners/__init__.py
cloudshell_firewall_cisco_asa.egg-info/PKG-INFO
cloudshell_firewall_cisco_asa.egg-info/SOURCES.txt
cloudshell_firewall_cisco_asa.egg-info/dependency_links.txt
cloudshell_firewall_cisco_asa.egg-info/requires.txt
cloudshell_firewall_cisco_asa.egg-info/top_level.txt
