Metadata-Version: 1.0
Name: cloudshell-firewall-cisco-asa
Version: 3.0.5
Summary: QualiSystems firewall Cisco ASA specific Package
Home-page: http://www.qualisystems.com/
Author: QualiSystems
Author-email: info@qualisystems.com
License: UNKNOWN
Platform: UNKNOWN
